chatthy/__init__.py
chatthy/__main__.py
chatthy/embeddings.hy
chatthy/client/__init__.py
chatthy/client/client-help.md
chatthy/client/client.hy
chatthy/client/interface.hy
chatthy/client/ptk_app.hy
chatthy/client/repl.hy
chatthy/client/state.hy
chatthy/server/completions.hy
chatthy/server/interface.hy
chatthy/server/rag.hy
chatthy/server/server.hy
chatthy/server/state.hy
chatthy/server/templates/instruct.toml
chatthy/tools/discuss.hy
chatthy/tools/tools.hy
chatthy-0.2.11.dist-info/licenses/LICENSE
chatthy-0.2.11.dist-info/METADATA
chatthy-0.2.11.dist-info/WHEEL
chatthy-0.2.11.dist-info/entry_points.txt
chatthy-0.2.11.dist-info/top_level.txt
chatthy-0.2.11.dist-info/RECORD
