Metadata-Version: 2.4
Name: chatthy
Version: 0.2.11
Summary: A minimal LLM network chat server/client app.
Author-email: Ati Sharma <ati+chatthy@agalmic.ltd>
License-Expression: AGPL-3.0-or-later
Project-URL: Repository, https://github.com/atisharma/chatthy
Keywords: hy,hylang,zeromq,llm,openai,anthropic
Classifier: Programming Language :: Python :: 3
Classifier: Programming Language :: Python :: 3.11
Classifier: Programming Language :: Python :: 3.12
Classifier: Programming Language :: Python :: 3.13
Classifier: Programming Language :: Python :: 3.14
Classifier: Programming Language :: Lisp
Requires-Python: >=3.11
License-File: LICENSE
Requires-Dist: clipman
Requires-Dist: colorist
Requires-Dist: flatlatex
Requires-Dist: hy>=1.0
Requires-Dist: hyjinx[zmq]
Requires-Dist: hyrule
Requires-Dist: platformdirs
Requires-Dist: prompt_toolkit
Requires-Dist: pygments
Requires-Dist: tabulated[widechars]
Requires-Dist: tiktoken
Requires-Dist: toolz
Provides-Extra: server
Requires-Dist: hyjinx[dev]; extra == "server"
Requires-Dist: trag; extra == "server"
Requires-Dist: fvdb; extra == "server"
Dynamic: license-file
